{
  "name" : "Chef and Ingredients",
  "testType" : "SINGLE",
  "input" : {
    "type" : "STANDARD",
    "fileName" : "input.txt"
  },
  "output" : {
    "type" : "STANDARD",
    "fileName" : "output.txt"
  },
  "tests" : [ {
    "input" : "2\n2 1\n3 3\n",
    "output" : "0\n2\n",
    "index" : 0,
    "active" : true
  } ],
  "location" : "src/CodeForces",
  "vmArgs" : "-Xmx256M",
  "mainClass" : "Main",
  "taskClass" : "CodeForces.ChefAndIngredients",
  "checkerClass" : "net.egork.chelper.checkers.TokenChecker",
  "checkerParameters" : "",
  "testClasses" : [ ],
  "date" : "2019.06.16",
  "contestName" : "CodeChef - JUNE Challenge 2019 Division 2",
  "truncate" : true,
  "inputClass" : "java.util.Scanner",
  "outputClass" : "java.io.PrintWriter",
  "includeLocale" : false,
  "failOnOverflow" : false,
  "interactive" : false,
  "interactor" : "net.egork.chelper.tester.Interactor"
}